jutuldarcy/__init__.py
jutuldarcy/conversion.py
jutuldarcy/julia_import.py
jutuldarcy/juliapkg.json
jutuldarcy/meshes.py
jutuldarcy/model.py
jutuldarcy/parsing.py
jutuldarcy/plotting.py
jutuldarcy/reservoir.py
jutuldarcy/simulate.py
jutuldarcy/systems.py
jutuldarcy/units.py
jutuldarcy/utils.py
jutuldarcy/wells.py
jutuldarcy-1.1.0.dist-info/licenses/LICENSE
jutuldarcy-1.1.0.dist-info/METADATA
jutuldarcy-1.1.0.dist-info/WHEEL
jutuldarcy-1.1.0.dist-info/top_level.txt
jutuldarcy-1.1.0.dist-info/RECORD
