Metadata-Version: 2.4
Name: jutuldarcy
Version: 1.1.0
Summary: Reservoir simulation with JutulDarcy in Python.
Author-email: Olav Møyner <olav.moyner@gmail.com>
Maintainer-email: Olav Møyner <olav.moyner@gmail.com>
License-Expression: MIT
Project-URL: Repository, https://github.com/sintefmath/PyJutulDarcy
Project-URL: Julia repository, https://github.com/sintefmath/JutulDarcy.jl
Project-URL: Documentation, https://sintefmath.github.io/JutulDarcy.jl/dev/
Keywords: reservoir simulation,jutuldarcy
Classifier: Development Status :: 4 - Beta
Classifier: Programming Language :: Python :: 3
Classifier: Programming Language :: Python :: 3.9
Classifier: Programming Language :: Python :: 3.10
Classifier: Programming Language :: Python :: 3.11
Classifier: Programming Language :: Python :: 3.12
Classifier: Programming Language :: Python :: 3.13
Classifier: Programming Language :: Python :: 3 :: Only
Requires-Python: >=3.9
License-File: LICENSE
Requires-Dist: juliacall==0.9.24
Requires-Dist: numpy<3.0.0,>=1.13.0
Requires-Dist: juliapkg>=0.1
Dynamic: license-file
